voronoice/__init__.py
voronoice/__version__.py
voronoice-2023.0.0.dist-info/METADATA
voronoice-2023.0.0.dist-info/WHEEL
voronoice-2023.0.0.dist-info/top_level.txt
voronoice-2023.0.0.dist-info/RECORD
